wiscopy/__init__.py
wiscopy/_version.py
wiscopy/data.py
wiscopy/interface.py
wiscopy/process.py
wiscopy/schema.py
wiscopy/variables.py
wiscopy-0.1.5.dist-info/METADATA
wiscopy-0.1.5.dist-info/WHEEL
wiscopy-0.1.5.dist-info/licenses/LICENSE
wiscopy-0.1.5.dist-info/RECORD
