Metadata-Version: 2.4
Name: wiscopy
Version: 0.1.5
Summary: A Python API wrapper for the Wisconsin environmental mesonet API: Wisconet
Project-URL: Homepage, https://github.com/UW-Madison-DSI/wiscopy
Project-URL: Issues, https://github.com/UW-Madison-DSI/wiscopy/issues
Author-email: Iain McConnell <ilmcconnell@github.id>
License-Expression: MIT
License-File: LICENSE
Classifier: Operating System :: OS Independent
Classifier: Programming Language :: Python :: 3
Requires-Python: >=3.10
Requires-Dist: httpx>=0.28.1
Requires-Dist: pandas>=2.2.3
Requires-Dist: pydantic>=2.10.6
Provides-Extra: plot
Requires-Dist: hvplot>=0.11.2; extra == 'plot'
Requires-Dist: matplotlib>=3.10.1; extra == 'plot'
